agentfactory/__init__.py
agentfactory/version.py
agentfactory-0.0.0.dist-info/LICENSE
agentfactory-0.0.0.dist-info/METADATA
agentfactory-0.0.0.dist-info/WHEEL
agentfactory-0.0.0.dist-info/entry_points.txt
agentfactory-0.0.0.dist-info/top_level.txt
agentfactory-0.0.0.dist-info/RECORD
