Metadata-Version: 2.1
Name: agentfactory
Version: 0.0.0
Summary: AgentFactory
Home-page: https://github.com/wangxingjun778/AgentFactory
Author: wangxingjun778
Author-email: wangxingjun778@163.com
License: Apache License 2.0
Keywords: Agent,Reinforcement Learning,Tool Learning,LLM,Multimodal
Classifier: Development Status :: 4 - Beta
Classifier: License :: OSI Approved :: Apache Software License
Classifier: Operating System :: OS Independent
Classifier: Programming Language :: Python :: 3
Classifier: Programming Language :: Python :: 3.8
Classifier: Programming Language :: Python :: 3.9
Classifier: Programming Language :: Python :: 3.10
Classifier: Programming Language :: Python :: 3.11
Classifier: Programming Language :: Python :: 3.12
License-File: LICENSE
Requires-Dist: numpy
